README.md
setup.py
mobula/Defines.py
mobula/Net.py
mobula/__init__.py
mobula/wrapper.py
mobula.egg-info/PKG-INFO
mobula.egg-info/SOURCES.txt
mobula.egg-info/dependency_links.txt
mobula.egg-info/requires.txt
mobula.egg-info/top_level.txt
mobula/layers/Accuracy.py
mobula/layers/BatchNorm.py
mobula/layers/Concat.py
mobula/layers/ContrastiveLoss.py
mobula/layers/Conv.py
mobula/layers/ConvT.py
mobula/layers/Crop.py
mobula/layers/CrossEntropy.py
mobula/layers/Data.py
mobula/layers/Dropout.py
mobula/layers/Eltwise.py
mobula/layers/FC.py
mobula/layers/L1Loss.py
mobula/layers/Layer.py
mobula/layers/LossLayer.py
mobula/layers/MSE.py
mobula/layers/MergeTest.py
mobula/layers/PReLU.py
mobula/layers/Pool.py
mobula/layers/ReLU.py
mobula/layers/Reshape.py
mobula/layers/SELU.py
mobula/layers/Sigmoid.py
mobula/layers/SigmoidCrossEntropy.py
mobula/layers/Slice.py
mobula/layers/SmoothL1Loss.py
mobula/layers/Softmax.py
mobula/layers/SoftmaxWithLoss.py
mobula/layers/SplitTest.py
mobula/layers/Tanh.py
mobula/layers/__init__.py
mobula/layers/utils/Defines.py
mobula/layers/utils/LayerManager.py
mobula/layers/utils/MultiInput.py
mobula/layers/utils/MultiOutput.py
mobula/layers/utils/NullNet.py
mobula/layers/utils/VModel.py
mobula/layers/utils/__init__.py
mobula/operators/Add.py
mobula/operators/Exp.py
mobula/operators/Layer.py
mobula/operators/Log.py
mobula/operators/Multiply.py
mobula/operators/Negative.py
mobula/operators/Power.py
mobula/operators/ReduceMax.py
mobula/operators/ReduceMean.py
mobula/operators/ReduceMin.py
mobula/operators/Subtract.py
mobula/operators/__init__.py
mobula/solvers/LRUpdater.py
mobula/solvers/Momentum.py
mobula/solvers/SGD.py
mobula/solvers/Solver.py
mobula/solvers/__init__.py