Metadata-Version: 1.1
Name: mobula
Version: 1.0.0
Summary: A Lightweight & Flexible Deep Learning (Neural Network) Framework in Python
Home-page: https://github.com/wkcn/mobula
Author: wkcn
Author-email: wkcn@live.cn
License: MIT
Keywords: Deep Learning Framework in Python
Platform: UNKNOWN
Classifier: Programming Language :: Python
Classifier: Programming Language :: Python :: 2
Classifier: Programming Language :: Python :: 3
Classifier: Topic :: Scientific/Engineering :: Mathematics
Classifier: License :: OSI Approved :: MIT License
